prosemble/__init__.py
prosemble/core/__init__.py
prosemble/core/distance.py
prosemble/core/initializers.py
prosemble/datasets/__init__.py
prosemble/datasets/dataset.py
prosemble/models/__init__.py
prosemble/models/afcm.py
prosemble/models/bgpc.py
prosemble/models/fcm.py
prosemble/models/fpcm.py
prosemble/models/hcm.py
prosemble/models/ipcm.py
prosemble/models/ipcm_2.py
prosemble/models/kafcm.py
prosemble/models/kfcm.py
prosemble/models/kfpcm.py
prosemble/models/kipcm.py
prosemble/models/kipcm2.py
prosemble/models/kmeans.py
prosemble/models/knn.py
prosemble/models/kpcm.py
prosemble/models/kpfcm.py
prosemble/models/npc.py
prosemble/models/pcm.py
prosemble/models/pfcm.py
prosemble/models/som.py
prosemble-0.9.2.dist-info/LICENSE
prosemble-0.9.2.dist-info/METADATA
prosemble-0.9.2.dist-info/WHEEL
prosemble-0.9.2.dist-info/dependency_links.txt
prosemble-0.9.2.dist-info/top_level.txt
prosemble-0.9.2.dist-info/RECORD
